audio_separator/__init__.py
audio_separator/separator/__init__.py
audio_separator/separator/common_separator.py
audio_separator/separator/separator.py
audio_separator/separator/architectures/__init__.py
audio_separator/separator/architectures/demucs_separator.py
audio_separator/separator/architectures/mdx_separator.py
audio_separator/separator/architectures/mdxc_separator.py
audio_separator/separator/architectures/vr_separator.py
audio_separator/separator/uvr_lib_v5/__init__.py
audio_separator/separator/uvr_lib_v5/mdxnet.py
audio_separator/separator/uvr_lib_v5/modules.py
audio_separator/separator/uvr_lib_v5/playsound.py
audio_separator/separator/uvr_lib_v5/pyrb.py
audio_separator/separator/uvr_lib_v5/results.py
audio_separator/separator/uvr_lib_v5/spec_utils.py
audio_separator/separator/uvr_lib_v5/stft.py
audio_separator/separator/uvr_lib_v5/tfc_tdf_v3.py
audio_separator/separator/uvr_lib_v5/demucs/__init__.py
audio_separator/separator/uvr_lib_v5/demucs/__main__.py
audio_separator/separator/uvr_lib_v5/demucs/apply.py
audio_separator/separator/uvr_lib_v5/demucs/demucs.py
audio_separator/separator/uvr_lib_v5/demucs/filtering.py
audio_separator/separator/uvr_lib_v5/demucs/hdemucs.py
audio_separator/separator/uvr_lib_v5/demucs/htdemucs.py
audio_separator/separator/uvr_lib_v5/demucs/model.py
audio_separator/separator/uvr_lib_v5/demucs/model_v2.py
audio_separator/separator/uvr_lib_v5/demucs/pretrained.py
audio_separator/separator/uvr_lib_v5/demucs/repo.py
audio_separator/separator/uvr_lib_v5/demucs/spec.py
audio_separator/separator/uvr_lib_v5/demucs/states.py
audio_separator/separator/uvr_lib_v5/demucs/tasnet.py
audio_separator/separator/uvr_lib_v5/demucs/tasnet_v2.py
audio_separator/separator/uvr_lib_v5/demucs/transformer.py
audio_separator/separator/uvr_lib_v5/demucs/utils.py
audio_separator/separator/uvr_lib_v5/vr_network/__init__.py
audio_separator/separator/uvr_lib_v5/vr_network/layers.py
audio_separator/separator/uvr_lib_v5/vr_network/layers_new.py
pafts-1.0.1.dist-info/LICENSE
pafts-1.0.1.dist-info/METADATA
pafts-1.0.1.dist-info/WHEEL
pafts-1.0.1.dist-info/top_level.txt
pafts-1.0.1.dist-info/RECORD
