Metadata-Version: 2.1
Name: pafts
Version: 1.0.1
Summary: Library That Preprocessing Audio For TTS.
Home-page: https://github.com/harmlessman/PAFTS
Author: harmlessman
Author-email: harmlessman17@gmail.com
License: MIT License
Classifier: Intended Audience :: Science/Research
Classifier: Intended Audience :: Developers
Classifier: License :: OSI Approved :: MIT License
Classifier: Operating System :: OS Independent
Classifier: Topic :: Software Development :: Libraries :: Python Modules
Classifier: Programming Language :: Python
Classifier: Programming Language :: Python :: 3
Classifier: Programming Language :: Python :: 3.10
Requires-Python: >=3.10, <3.11
License-File: LICENSE
Requires-Dist: spleeter
Requires-Dist: pydub
Requires-Dist: SpeechRecognition
Requires-Dist: tqdm
Requires-Dist: audio-separator[gpu]
Requires-Dist: requests (>=2)
Requires-Dist: librosa (>=0.10)
Requires-Dist: samplerate (==0.1.0)
Requires-Dist: six (>=1.16)
Requires-Dist: onnx (>=1.14)
Requires-Dist: onnx2torch (>=1.5)
Requires-Dist: onnxruntime (>=1.17)
Requires-Dist: onnxruntime-gpu (>=1.17)
Requires-Dist: julius (>=0.2)
Requires-Dist: diffq (>=0.2)
Requires-Dist: einops (>=0.7)
Requires-Dist: pyyaml
Requires-Dist: ml-collections
Requires-Dist: resampy (>=0.4)
Requires-Dist: beartype (==0.18.5)
Requires-Dist: rotary-embedding-torch (==0.6.1)
Requires-Dist: scipy (==1.13.0)
Requires-Dist: silero-vad
Requires-Dist: pyannote.audio
Requires-Dist: openai-whisper
